madai/__init__.py
madai/chi2.py
madai/cli.py
madai/spearman.py
madai/utils.py
madai-0.2.2.dist-info/entry_points.txt
madai-0.2.2.dist-info/WHEEL
madai-0.2.2.dist-info/METADATA
madai-0.2.2.dist-info/RECORD
