Metadata-Version: 2.1
Name: madai
Version: 0.2.2
Summary: 
Author: sobamchan
Author-email: oh.sore.sore.soutarou@gmail.com
Requires-Python: >=3.9,<3.12
Classifier: Programming Language :: Python :: 3
Classifier: Programming Language :: Python :: 3.9
Classifier: Programming Language :: Python :: 3.10
Classifier: Programming Language :: Python :: 3.11
Requires-Dist: nltk (>=3.8.1,<4.0.0)
Requires-Dist: pyvi (>=0.1.1,<0.2.0)
Requires-Dist: scipy (>=1.10.1,<2.0.0)
Requires-Dist: sienna (>=0.2.2,<0.3.0)
Requires-Dist: spacy (>=3.5.2,<4.0.0)
Requires-Dist: typer (==0.7.0)
